src/python/__init__.py
src/python/main.py
uni_utils-1.0.0.dist-info/LICENSE
uni_utils-1.0.0.dist-info/METADATA
uni_utils-1.0.0.dist-info/WHEEL
uni_utils-1.0.0.dist-info/entry_points.txt
uni_utils-1.0.0.dist-info/top_level.txt
uni_utils-1.0.0.dist-info/RECORD
