Metadata-Version: 2.1
Name: uni-utils
Version: 1.0.0
Summary: A unified toolkit for all languages
Home-page: https://github.com/yxwzaxns/uni-utils
Author: aong
Author-email: yxwzaxns@gmail.com
License: https://github.com/yxwzaxns/uni-utils/blob/master/LICENSE
Platform: UNKNOWN
Classifier: Programming Language :: Python :: 3
Classifier: Programming Language :: Python :: 3.3
Classifier: Programming Language :: Python :: 3.4
Classifier: Programming Language :: Python :: Implementation :: CPython
Classifier: Programming Language :: Python :: Implementation :: PyPy
Requires-Python: >=3.6
